{"cookies": [{"name": "_csrf", "value": "YfiHMgSKR0R2ginDPh_alsvS", "domain": ".ft.com", "path": "/", "expires": -1, "httpOnly": true, "secure": true, "sameSite": "Strict"}, {"name": "spoor-id", "value": "cm82r8ecd00013570aawj39ye", "domain": ".ft.com", "path": "/", "expires": 1773128580.973742, "httpOnly": false, "secure": false, "sameSite": "Lax"}, {"name": "FTSession_s", "value": "0x7WLpDZj0QM04C4FrBMJcP90wAAAZV_Aadhw8I.MEYCIQD_nFwf1cWf1y_Z_qyYuY14KdrIMGPBO03b8RgPmXSwNgIhAKWNF06oikRxuLJwoBqxvMR8Tik9epT-Kq2bgUttPGt5", "domain": ".ft.com", "path": "/", "expires": 1757490169.795774, "httpOnly": false, "secure": true, "sameSite": "Lax"}, {"name": "FTLogin", "value": "beta", "domain": ".ft.com", "path": "/", "expires": 1757490169.795841, "httpOnly": false, "secure": false, "sameSite": "Lax"}, {"name": "FTAllocation", "value": "1ed62e90-d98f-440c-80b8-16b04c25c3fd", "domain": ".ft.com", "path": "/", "expires": 1773128580.973697, "httpOnly": false, "secure": false, "sameSite": "Lax"}, {"name": "o-typography-fonts-loaded", "value": "1", "domain": ".ft.com", "path": "/", "expires": 1742197381.307222, "httpOnly": false, "secure": false, "sameSite": "Lax"}, {"name": "_cb", "value": "CAxxXQ8gJ9gCQOa3U", "domain": ".ft.com", "path": "/", "expires": 1775720571, "httpOnly": false, "secure": true, "sameSite": "Lax"}, {"name": "_chartbeat2", "value": ".1741592571181.1741592571181.1.CtEIMmC6swq_B5geFOoQ2k4Bsa16_.1", "domain": ".ft.com", "path": "/", "expires": 1775720571, "httpOnly": false, "secure": true, "sameSite": "Lax"}, {"name": "_cb_svref", "value": "https%3A%2F%2Faccounts.ft.com%2F", "domain": ".ft.com", "path": "/", "expires": 1741594371, "httpOnly": false, "secure": true, "sameSite": "Lax"}, {"name": "__gads", "value": "ID=777027fe5660df17:T=1741592572:RT=1741592572:S=ALNI_MYbnLdJpILn7xctZ4qN4IynSya1JA", "domain": ".ft.com", "path": "/", "expires": 1775288572, "httpOnly": false, "secure": true, "sameSite": "None"}, {"name": "__eoi", "value": "ID=8df60ee90d40292b:T=1741592572:RT=1741592572:S=AA-AfjavhJpO38jyA0hFPLzndwNa", "domain": ".ft.com", "path": "/", "expires": 1757144572, "httpOnly": false, "secure": true, "sameSite": "None"}, {"name": "IDE", "value": "AHWqTUl6QVKFfyD9zQ1LfC4pyaEeK78dYAkb1Qf58Mfu7ES3q2BdGdn7EeQlVe2t1j4", "domain": ".doubleclick.net", "path": "/", "expires": 1776152572.769174, "httpOnly": true, "secure": true, "sameSite": "None"}, {"name": "xnpe_d6e5bd4c-9228-11eb-a414-9a67e462410e", "value": "db19b4d9-6a46-4499-bb1c-60914b07ca24", "domain": "bloomreach.ft.com", "path": "/", "expires": 1757317374.204719, "httpOnly": false, "secure": true, "sameSite": "None"}, {"name": "__exponea_etc__", "value": "db19b4d9-6a46-4499-bb1c-60914b07ca24", "domain": ".www.ft.com", "path": "/", "expires": 1757317373, "httpOnly": false, "secure": true, "sameSite": "None"}, {"name": "__exponea_time2__", "value": "-0.11459875106811523", "domain": ".www.ft.com", "path": "/", "expires": 1757317373, "httpOnly": false, "secure": true, "sameSite": "None"}, {"name": "FTCookieConsentGDPR", "value": "true", "domain": ".ft.com", "path": "/", "expires": 1757490174.765567, "httpOnly": false, "secure": false, "sameSite": "Lax"}, {"name": "usnatUUID", "value": "b7abcd80-f61c-4a06-8bac-2ea98a11d901", "domain": ".ft.com", "path": "/", "expires": 1773128574.785952, "httpOnly": false, "secure": true, "sameSite": "None"}, {"name": "FTConsent", "value": "behaviouraladsOnsite%3Aon%2CcookiesOnsite%3Aon%2CcookiesUseraccept%3Aoff%2CdemographicadsOnsite%3Aon%2CenhancementByemail%3Aoff%2CenhancementByfax%3Aoff%2CenhancementByphonecall%3Aoff%2CenhancementBypost%3Aoff%2CenhancementBysms%3Aoff%2CmarketingByemail%3Aoff%2CmarketingByfax%3Aoff%2CmarketingByphonecall%3Aoff%2CmarketingBypost%3Aoff%2CmarketingBysms%3Aoff%2CmembergetmemberByemail%3Aoff%2CpermutiveadsOnsite%3Aon%2CpersonalisedmarketingOnsite%3Aon%2CprogrammaticadsOnsite%3Aon%2CrecommendedcontentOnsite%3Aon", "domain": ".ft.com", "path": "/", "expires": 1757490178.973482, "httpOnly": false, "secure": false, "sameSite": "Lax"}, {"name": "OriginalReferer", "value": "None", "domain": ".ft.com", "path": "/", "expires": 1741594380.973587, "httpOnly": false, "secure": false, "sameSite": "Lax"}, {"name": "FtComEntryPoint", "value": "/content/df86ab14-5b02-4992-9afc-c694be0b7fb0", "domain": ".ft.com", "path": "/", "expires": 1741594380.973621, "httpOnly": false, "secure": false, "sameSite": "Lax"}, {"name": "ft-access-decision-policy", "value": "DENIED_SUBX_STANDARD_8_30_V3", "domain": ".ft.com", "path": "/", "expires": -1, "httpOnly": false, "secure": false, "sameSite": "Lax"}, {"name": "_chartbeat4", "value": "t=BYcqk2cavatCSpOkRDS9gJuQS8OT&E=5&x=0&c=0.16&y=8436&w=768", "domain": ".ft.com", "path": "/", "expires": 1741592640, "httpOnly": false, "secure": true, "sameSite": "Lax"}, {"name": "li_sugr", "value": "9fa9ea26-8cd4-43be-9954-187ce26cb9cf", "domain": ".linkedin.com", "path": "/", "expires": 1749368582.271756, "httpOnly": false, "secure": true, "sameSite": "None"}, {"name": "bcookie", "value": "\"v=2&363fc86e-7c38-4594-867d-4a0048eed2bc\"", "domain": ".linkedin.com", "path": "/", "expires": 1773128583.271874, "httpOnly": false, "secure": true, "sameSite": "None"}, {"name": "lidc", "value": "\"b=VGST08:s=V:r=V:a=V:p=V:g=3149:u=1:x=1:i=1741592581:t=1741678981:v=2:sig=AQHTetosb1b225xqZHfUE4kjcOC0aO3k\"", "domain": ".linkedin.com", "path": "/", "expires": 1741678982.46963, "httpOnly": false, "secure": true, "sameSite": "None"}, {"name": "_uetsid", "value": "4b250020fd8311efbcdec5a6398c5c7c", "domain": ".ft.com", "path": "/", "expires": 1741678981, "httpOnly": false, "secure": false, "sameSite": "Lax"}, {"name": "_uetvid", "value": "4b252c60fd8311efa01bc36a5fdb7ee3", "domain": ".ft.com", "path": "/", "expires": 1775288581, "httpOnly": false, "secure": false, "sameSite": "Lax"}, {"name": "MUID", "value": "218A06694CD761A6144413C24DA8602E", "domain": ".bing.com", "path": "/", "expires": 1775288583.710459, "httpOnly": false, "secure": true, "sameSite": "None"}, {"name": "MR", "value": "0", "domain": ".bat.bing.com", "path": "/", "expires": 1742197382.608369, "httpOnly": false, "secure": true, "sameSite": "None"}, {"name": "muc_ads", "value": "20127aba-2e25-48f6-8ae5-aa7aa8c7b3eb", "domain": ".t.co", "path": "/", "expires": 1776152581.714295, "httpOnly": false, "secure": true, "sameSite": "None"}, {"name": "__cf_bm", "value": "6sxBriN6mw_VZCLNEu71gb1GU_8C7i.atwdxUwl8pFw-1741592581-1.0.1.1-INyS4PhalAiIKxs9XPoICldyAopwrsryEB0zbWrALujegtFXMCyK.I3ePSwHBWCxU.ECgAXsGgmVFthZYWZ9Oa6RFjsq5hw4Ar5QexxTVFw", "domain": ".t.co", "path": "/", "expires": 1741594381.714465, "httpOnly": true, "secure": true, "sameSite": "None"}, {"name": "UserMatchHistory", "value": "AQLKY4bLlXYQpQAAAZV_AdXTr3zAvaJnlGzSf0owANCQCa5jnVpmWijucOXfn4-KJGktcfIBZpABmA", "domain": ".linkedin.com", "path": "/", "expires": 1744184581.723061, "httpOnly": false, "secure": true, "sameSite": "None"}, {"name": "AnalyticsSyncHistory", "value": "AQI2Q6CRi8XiegAAAZV_AdXTCbUGsGGdIThMRhqf7La9ZCypzk1O4-wAGPizo2U-XNrtYnHpW_hIKPkXEiVTXg", "domain": ".linkedin.com", "path": "/", "expires": 1744184581.723165, "httpOnly": false, "secure": true, "sameSite": "None"}, {"name": "ar_debug", "value": "1", "domain": ".doubleclick.net", "path": "/", "expires": 1744184581.76185, "httpOnly": true, "secure": true, "sameSite": "None"}, {"name": "CLID", "value": "f1df011a5d6e4bada17a9eabed300a00.20250310.20260310", "domain": "www.clarity.ms", "path": "/", "expires": 1773128581.775614, "httpOnly": true, "secure": true, "sameSite": "None"}, {"name": "receive-cookie-deprecation", "value": "1", "domain": ".doubleclick.net", "path": "/", "expires": 1757144581.78271, "httpOnly": true, "secure": true, "sameSite": "None"}, {"name": "guest_id_marketing", "value": "v1%3A174159258169446472", "domain": ".twitter.com", "path": "/", "expires": 1776152581.796843, "httpOnly": false, "secure": true, "sameSite": "None"}, {"name": "guest_id_ads", "value": "v1%3A174159258169446472", "domain": ".twitter.com", "path": "/", "expires": 1776152581.796973, "httpOnly": false, "secure": true, "sameSite": "None"}, {"name": "personalization_id", "value": "\"v1_sED0O648AFSNdnlvBCdbGQ==\"", "domain": ".twitter.com", "path": "/", "expires": 1776152581.797007, "httpOnly": false, "secure": true, "sameSite": "None"}, {"name": "guest_id", "value": "v1%3A174159258169446472", "domain": ".twitter.com", "path": "/", "expires": 1776152581.797035, "httpOnly": false, "secure": true, "sameSite": "None"}, {"name": "_clck", "value": "7cskss%7C2%7Cfu3%7C0%7C1895", "domain": ".ft.com", "path": "/", "expires": 1773128581, "httpOnly": false, "secure": false, "sameSite": "Lax"}, {"name": "dicbo_id", "value": "%7B%22dicbo_fetch%22%3A1741592582012%7D", "domain": "www.ft.com", "path": "/", "expires": 1741592882, "httpOnly": false, "secure": false, "sameSite": "Lax"}, {"name": "bscookie", "value": "\"v=1&202503100743012592d5cc-448c-43b7-81d7-12ffbaf98e8dAQF9-XDmThHTiRWwu6J00DqZI5yhQfbL\"", "domain": ".www.linkedin.com", "path": "/", "expires": 1773128582.048613, "httpOnly": true, "secure": true, "sameSite": "None"}, {"name": "zit.data.toexclude", "value": "0", "domain": ".ft.com", "path": "/", "expires": 1773128582, "httpOnly": false, "secure": false, "sameSite": "Lax"}, {"name": "_sxh", "value": "1590,", "domain": ".ft.com", "path": "/", "expires": 1744184582, "httpOnly": false, "secure": false, "sameSite": "Lax"}, {"name": "_clsk", "value": "xcglzl%7C1741592582633%7C1%7C0%7Cn.clarity.ms%2Fcollect", "domain": ".ft.com", "path": "/", "expires": 1741678982, "httpOnly": false, "secure": false, "sameSite": "Lax"}, {"name": "MR", "value": "0", "domain": ".c.bing.com", "path": "/", "expires": 1742197383.710598, "httpOnly": false, "secure": true, "sameSite": "None"}, {"name": "SRM_B", "value": "218A06694CD761A6144413C24DA8602E", "domain": ".c.bing.com", "path": "/", "expires": 1775288583.710643, "httpOnly": false, "secure": true, "sameSite": "None"}, {"name": "SM", "value": "C", "domain": ".c.clarity.ms", "path": "/", "expires": -1, "httpOnly": false, "secure": true, "sameSite": "None"}, {"name": "MUID", "value": "218A06694CD761A6144413C24DA8602E", "domain": ".clarity.ms", "path": "/", "expires": 1775288582.806684, "httpOnly": false, "secure": true, "sameSite": "None"}, {"name": "MR", "value": "0", "domain": ".c.clarity.ms", "path": "/", "expires": 1742197382.806755, "httpOnly": false, "secure": true, "sameSite": "None"}, {"name": "ANONCHK", "value": "0", "domain": ".c.clarity.ms", "path": "/", "expires": 1741593182.806889, "httpOnly": false, "secure": true, "sameSite": "None"}, {"name": "__adblocker", "value": "false", "domain": "www.ft.com", "path": "/", "expires": 1741592882, "httpOnly": false, "secure": false, "sameSite": "Lax"}, {"name": "dtId", "value": "D250310DWwIxuDBvQDVFDBIon%2bQNp%2f8xwRQmP0V6cemX%2bOzH7M%3d", "domain": ".zeddit.com", "path": "/", "expires": 1773128583.005185, "httpOnly": true, "secure": true, "sameSite": "None"}, {"name": "sessionId", "value": "3780463", "domain": ".ft.com", "path": "/", "expires": 1741593783, "httpOnly": false, "secure": false, "sameSite": "Lax"}, {"name": "_sxoSource", "value": "Organic", "domain": ".ft.com", "path": "/", "expires": 1741593783, "httpOnly": false, "secure": false, "sameSite": "Lax"}, {"name": "_sanba", "value": "0", "domain": ".ft.com", "path": "/", "expires": 1744184583, "httpOnly": false, "secure": false, "sameSite": "Lax"}, {"name": "_sf", "value": "1", "domain": ".ft.com", "path": "/", "expires": 1741593783, "httpOnly": false, "secure": false, "sameSite": "Lax"}, {"name": "_sxo", "value": "{\"R\":0,\"tP\":0,\"tM\":0,\"sP\":1,\"sM\":0,\"dP\":1,\"dM\":0,\"dS\":1,\"tS\":0,\"cPs\":1,\"lPs\":[0],\"sSr\":0,\"sWids\":[],\"wN\":0,\"cdT\":0,\"F\":1,\"RF\":1,\"w\":0,\"SFreq\":1,\"last_wid\":0,\"bid\":1036,\"accNo\":\"\",\"clientId\":\"\",\"isEmailAud\":0,\"isPanelAud\":0,\"hDW\":0,\"isRegAud\":0,\"isExAud\":0,\"isDropoff\":0,\"devT\":0,\"exPW\":0,\"Nba\":-1,\"userName\":\"\",\"dataLayer\":\"\",\"localSt\":\"\",\"emailId\":\"\",\"emailTag\":\"\",\"subTag\":\"\",\"lVd\":\"2025-3-10\",\"oS\":\"D250310DWwIxuDBvQDVFDBIon+QNp/8xwRQmP0V6cemX+OzH7M=\",\"cPu\":\"https://www.ft.com/content/df86ab14-5b02-4992-9afc-c694be0b7fb0\",\"pspv\":0,\"pslv\":0,\"pssSr\":0,\"pswN\":0,\"psdS\":0,\"pscdT\":0,\"RP\":0,\"TPrice\":0,\"ML\":\"\",\"isReCaptchaOn\":false,\"reCaptchaSiteKey\":\"\",\"reCaptchaSecretKey\":\"\",\"extRefer\":\"\",\"dM2\":0,\"tM2\":0,\"sM2\":0,\"RA\":0,\"ToBlock\":-1,\"CC\":null,\"groupName\":null}", "domain": ".ft.com", "path": "/", "expires": 1773128583, "httpOnly": false, "secure": false, "sameSite": "Lax"}, {"name": "MSPTC", "value": "Zro5W0DuGFjH8q0DAHCJ4J6LWzYe3l1SjoH0-7N6Jh4", "domain": ".bing.com", "path": "/", "expires": 1775288584.35323, "httpOnly": false, "secure": true, "sameSite": "None"}, {"name": "dicbo_id", "value": "%7B%22dicbo_fetch%22%3A1741592583586%7D", "domain": "accounts.ft.com", "path": "/", "expires": 1741592883, "httpOnly": false, "secure": false, "sameSite": "Lax"}, {"name": "_rdt_uuid", "value": "1741592581310.e2d152b9-e1a1-4cda-bc7e-55d45734ab2b", "domain": ".ft.com", "path": "/", "expires": 1749368602, "httpOnly": false, "secure": true, "sameSite": "Strict"}, {"name": "_gcl_au", "value": "1.1.1448608099.1741592581.1022285653.1741592601.1741592605", "domain": ".ft.com", "path": "/", "expires": 1749368581, "httpOnly": false, "secure": false, "sameSite": "Lax"}], "origins": [{"origin": "https://accounts.ft.com", "localStorage": [{"name": "spoor-id", "value": "cm82r8ecd00013570aawj39ye"}, {"name": "o-tracking_session", "value": "{\"value\":\"cm82r8ecd00023570991vulab\",\"expiry\":1741594402451,\"timestamp\":1741592542621}"}]}, {"origin": "https://www.ft.com", "localStorage": [{"name": "__bm_m", "value": ""}, {"name": "_cb", "value": "CAxxXQ8gJ9gCQOa3U"}, {"name": "_uetvid_exp", "value": "Sat, 04 Apr 2026 07:43:01 GMT"}, {"name": "spoor-id", "value": "cm82r8ecd00013570aawj39ye"}, {"name": "_chartbeat2", "value": ".1741592571181.1741592571181.1.CtEIMmC6swq_B5geFOoQ2k4Bsa16_.1"}, {"name": "_ssh", "value": "3780463,"}, {"name": "_chartbeat4_expires", "value": "1741592640980"}, {"name": "_uetsid", "value": "4b250020fd8311efbcdec5a6398c5c7c"}, {"name": "_cb_expires", "value": "1775720571182"}, {"name": "_sp_non_keyed_local_state", "value": "{\"gdpr\":{\"_sp_v1_data\":\"1073203\",\"_sp_v1_p\":\"983\"},\"usnat\":{\"_sp_v1_data\":\"1073205\",\"_sp_v1_p\":\"223\"}}"}, {"name": "__bm_s", "value": ""}, {"name": "_cb_svref", "value": "https%3A%2F%2Faccounts.ft.com%2F"}, {"name": "_uetsid_exp", "value": "Tue, 11 Mar 2025 07:43:01 GMT"}, {"name": "_chartbeat2_expires", "value": "1775720571183"}, {"name": "_sp_local_state", "value": "{\"gdpr\":{\"mmsCookies\":[\"_sp_v1_ss=1:H4sIAAAAAAAAAItWqo5RKimOUbKKhjHySnNydGKUUpHYJWCJ6traWFwSSjpKxOgnXdmgclYsAJXVOoIvAQAA\"],\"propertyId\":31642,\"messageId\":0},\"usnat\":{\"mmsCookies\":[\"_sp_v1_ss=1:H4sIAAAAAAAAAItWqo5RKimOUbLKK83J0YlRSkVil4AlqmtrlXSGvrJYAB7rhbDrAAAA\"],\"propertyId\":31642,\"messageId\":0}}"}, {"name": "o-tracking_session", "value": "{\"value\":\"cm82r908a0000356skpwzimrx\",\"expiry\":1741594381252,\"timestamp\":1741592570986}"}, {"name": "__exponea_banner_event__671a1810561395f47fd04cae_last_show", "value": "1741592578462"}, {"name": "_sp_user_consent_31642", "value": "{\"gdpr\":{\"authId\":\"1ed62e90-d98f-440c-80b8-16b04c25c3fd\",\"uuid\":\"24919809-4ab1-4968-ac8c-3a9ab32453d5_39_41\",\"getMessageAlways\":false,\"applies\":true,\"customVendorsResponse\":{\"consentedVendors\":[{\"_id\":\"5f1b2fbeb8e05c3057240fbc\",\"name\":\"AdButler\",\"vendorType\":\"CUSTOM\"},{\"_id\":\"5f1b2fbdb8e05c306e139f26\",\"name\":\"Evidon\",\"vendorType\":\"CUSTOM\"},{\"_id\":\"5f1b2fbeb8e05c306e139f60\",\"name\":\"gskinner\",\"vendorType\":\"CUSTOM\"},{\"_id\":\"5ec515cab8e05c6bd60edc5f\",\"name\":\"Optimizely, Inc.\",\"vendorType\":\"CUSTOM\"}],\"consentedPurposes\":[{\"_id\":\"64a5910e8ed78606ddbbb3c9\",\"name\":\"Store and/or access information on a device\"},{\"_id\":\"64a5910e8ed78606ddbbb3e9\",\"name\":\"Use limited data to select advertising\"},{\"_id\":\"64a5910e8ed78606ddbbb407\",\"name\":\"Create profiles for personalised advertising\"},{\"_id\":\"64a5910e8ed78606ddbbb425\",\"name\":\"Use profiles to select personalised advertising\"},{\"_id\":\"64a5910e8ed78606ddbbb44f\",\"name\":\"Measure advertising performance\"},{\"_id\":\"64a5910e8ed78606ddbbb46e\",\"name\":\"Measure content performance\"},{\"_id\":\"64a5910e8ed78606ddbbb473\",\"name\":\"Understand audiences through statistics or combinations of data from different sources\"},{\"_id\":\"64a5910e8ed78606ddbbb491\",\"name\":\"Develop and improve services\"}],\"legIntPurposes\":[{\"_id\":\"64a5910e8ed78606ddbbb3e9\",\"name\":\"Use limited data to select advertising\"},{\"_id\":\"64a5910e8ed78606ddbbb44f\",\"name\":\"Measure advertising performance\"},{\"_id\":\"64a5910e8ed78606ddbbb473\",\"name\":\"Understand audiences through statistics or combinations of data from different sources\"},{\"_id\":\"64a5910e8ed78606ddbbb491\",\"name\":\"Develop and improve services\"}]},\"addtlConsent\":\"1~196.2072\",\"grants\":{\"5f1b2fbeb8e05c3057240fbc\":{\"vendorGrant\":true,\"purposeGrants\":{\"64a5910e8ed78606ddbbb3c9\":true,\"64a5910e8ed78606ddbbb3e9\":true,\"64a5910e8ed78606ddbbb407\":true,\"64a5910e8ed78606ddbbb425\":true,\"64a5910e8ed78606ddbbb44f\":true,\"64a5910e8ed78606ddbbb473\":true,\"64a5910e8ed78606ddbbb491\":true}},\"5f1b2fbdb8e05c306e139f26\":{\"vendorGrant\":true,\"purposeGrants\":{\"64a5910e8ed78606ddbbb3c9\":true,\"64a5910e8ed78606ddbbb3e9\":true,\"64a5910e8ed78606ddbbb407\":true,\"64a5910e8ed78606ddbbb425\":true,\"64a5910e8ed78606ddbbb44f\":true,\"64a5910e8ed78606ddbbb473\":true,\"64a5910e8ed78606ddbbb491\":true}},\"5f1b2fbeb8e05c306e139f60\":{\"vendorGrant\":true,\"purposeGrants\":{\"64a5910e8ed78606ddbbb3c9\":true,\"64a5910e8ed78606ddbbb3e9\":true,\"64a5910e8ed78606ddbbb407\":true,\"64a5910e8ed78606ddbbb425\":true,\"64a5910e8ed78606ddbbb44f\":true,\"64a5910e8ed78606ddbbb473\":true,\"64a5910e8ed78606ddbbb491\":true}},\"5e7ced57b8e05c5a7d171cda\":{\"vendorGrant\":true,\"purposeGrants\":{\"64a5910e8ed78606ddbbb3c9\":true,\"64a5910e8ed78606ddbbb3e9\":true,\"64a5910e8ed78606ddbbb407\":true,\"64a5910e8ed78606ddbbb425\":true,\"64a5910e8ed78606ddbbb44f\":true,\"64a5910e8ed78606ddbbb491\":true}},\"5e37fc3e56a5e6615502f9c5\":{\"vendorGrant\":true,\"purposeGrants\":{\"64a5910e8ed78606ddbbb3c9\":true,\"64a5910e8ed78606ddbbb44f\":true}},\"5f117325b8e05c065164a42c\":{\"vendorGrant\":true,\"purposeGrants\":{\"64a5910e8ed78606ddbbb3c9\":true,\"64a5910e8ed78606ddbbb3e9\":true,\"64a5910e8ed78606ddbbb407\":true,\"64a5910e8ed78606ddbbb425\":true,\"64a5910e8ed78606ddbbb44f\":true,\"64a5910e8ed78606ddbbb491\":true}},\"5e37fc3e56a5e66147767221\":{\"vendorGrant\":true,\"purposeGrants\":{\"64a5910e8ed78606ddbbb3c9\":true,\"64a5910e8ed78606ddbbb3e9\":true,\"64a5910e8ed78606ddbbb407\":true,\"64a5910e8ed78606ddbbb425\":true,\"64a5910e8ed78606ddbbb44f\":true}},\"5e37fc3e56a5e6615502f9c9\":{\"vendorGrant\":true,\"purposeGrants\":{\"64a5910e8ed78606ddbbb3c9\":true,\"64a5910e8ed78606ddbbb44f\":true,\"64a5910e8ed78606ddbbb46e\":true}},\"5efefe25b8e05c06542b2a77\":{\"vendorGrant\":true,\"purposeGrants\":{\"64a5910e8ed78606ddbbb3c9\":true,\"64a5910e8ed78606ddbbb44f\":true,\"64a5910e8ed78606ddbbb46e\":true,\"64a5910e8ed78606ddbbb473\":true,\"64a5910e8ed78606ddbbb491\":true}},\"5f0838a5b8e05c109c2b8404\":{\"vendorGrant\":true,\"purposeGrants\":{\"64a5910e8ed78606ddbbb3c9\":true,\"64a5910e8ed78606ddbbb44f\":true,\"64a5910e8ed78606ddbbb473\":true}},\"5e7ced57b8e05c485246cce2\":{\"vendorGrant\":true,\"purposeGrants\":{\"64a5910e8ed78606ddbbb3c9\":true,\"64a5910e8ed78606ddbbb3e9\":true,\"64a5910e8ed78606ddbbb407\":true,\"64a5910e8ed78606ddbbb425\":true,\"64a5910e8ed78606ddbbb44f\":true}},\"5f1aada6b8e05c306c0597d7\":{\"vendorGrant\":true,\"purposeGrants\":{\"64a5910e8ed78606ddbbb3c9\":true,\"64a5910e8ed78606ddbbb3e9\":true,\"64a5910e8ed78606ddbbb407\":true,\"64a5910e8ed78606ddbbb425\":true,\"64a5910e8ed78606ddbbb44f\":true,\"64a5910e8ed78606ddbbb473\":true,\"64a5910e8ed78606ddbbb491\":true}},\"5e37fc3e56a5e66147767233\":{\"vendorGrant\":true,\"purposeGrants\":{\"64a5910e8ed78606ddbbb3c9\":true,\"64a5910e8ed78606ddbbb3e9\":true,\"64a5910e8ed78606ddbbb407\":true,\"64a5910e8ed78606ddbbb425\":true,\"64a5910e8ed78606ddbbb44f\":true,\"64a5910e8ed78606ddbbb473\":true,\"64a5910e8ed78606ddbbb491\":true}},\"5f2d22a6b8e05c02aa283b3c\":{\"vendorGrant\":true,\"purposeGrants\":{\"64a5910e8ed78606ddbbb3c9\":true,\"64a5910e8ed78606ddbbb3e9\":true,\"64a5910e8ed78606ddbbb407\":true,\"64a5910e8ed78606ddbbb425\":true,\"64a5910e8ed78606ddbbb44f\":true,\"64a5910e8ed78606ddbbb473\":true,\"64a5910e8ed78606ddbbb491\":true}},\"5ef5c3a5b8e05c69980eaa5b\":{\"vendorGrant\":true,\"purposeGrants\":{\"64a5910e8ed78606ddbbb3c9\":true,\"64a5910e8ed78606ddbbb407\":true,\"64a5910e8ed78606ddbbb491\":true}},\"5f369a02b8e05c2f2d546a40\":{\"vendorGrant\":true,\"purposeGrants\":{\"64a5910e8ed78606ddbbb3c9\":true,\"64a5910e8ed78606ddbbb3e9\":true,\"64a5910e8ed78606ddbbb425\":true,\"64a5910e8ed78606ddbbb46e\":true,\"64a5910e8ed78606ddbbb473\":true}},\"5f2d22a6b8e05c02aa283b3b\":{\"vendorGrant\":true,\"purposeGrants\":{\"64a5910e8ed78606ddbbb3c9\":true,\"64a5910e8ed78606ddbbb3e9\":true,\"64a5910e8ed78606ddbbb407\":true,\"64a5910e8ed78606ddbbb425\":true,\"64a5910e8ed78606ddbbb44f\":true,\"64a5910e8ed78606ddbbb473\":true,\"64a5910e8ed78606ddbbb491\":true}},\"5f23e825b8e05c0ed30ea6ac\":{\"vendorGrant\":true,\"purposeGrants\":{\"64a5910e8ed78606ddbbb3c9\":true,\"64a5910e8ed78606ddbbb3e9\":true,\"64a5910e8ed78606ddbbb407\":true,\"64a5910e8ed78606ddbbb425\":true,\"64a5910e8ed78606ddbbb44f\":true,\"64a5910e8ed78606ddbbb46e\":true}},\"5f1aada5b8e05c306e139f01\":{\"vendorGrant\":true,\"purposeGrants\":{\"64a5910e8ed78606ddbbb3c9\":true,\"64a5910e8ed78606ddbbb3e9\":true,\"64a5910e8ed78606ddbbb407\":true,\"64a5910e8ed78606ddbbb425\":true,\"64a5910e8ed78606ddbbb44f\":true,\"64a5910e8ed78606ddbbb46e\":true,\"64a5910e8ed78606ddbbb473\":true,\"64a5910e8ed78606ddbbb491\":true}},\"5ee34ea4b8e05c16353f5bb7\":{\"vendorGrant\":true,\"purposeGrants\":{\"64a5910e8ed78606ddbbb3c9\":true,\"64a5910e8ed78606ddbbb44f\":true,\"64a5910e8ed78606ddbbb46e\":true,\"64a5910e8ed78606ddbbb473\":true,\"64a5910e8ed78606ddbbb491\":true}},\"5e865b36b8e05c48537f60a7\":{\"vendorGrant\":true,\"purposeGrants\":{\"64a5910e8ed78606ddbbb3c9\":true,\"64a5910e8ed78606ddbbb3e9\":true,\"64a5910e8ed78606ddbbb407\":true,\"64a5910e8ed78606ddbbb425\":true,\"64a5910e8ed78606ddbbb44f\":true,\"64a5910e8ed78606ddbbb491\":true}},\"5fa51b27a2286307ce61b623\":{\"vendorGrant\":true,\"purposeGrants\":{\"64a5910e8ed78606ddbbb3c9\":true,\"64a5910e8ed78606ddbbb3e9\":true,\"64a5910e8ed78606ddbbb407\":true,\"64a5910e8ed78606ddbbb425\":true,\"64a5910e8ed78606ddbbb44f\":true,\"64a5910e8ed78606ddbbb46e\":true,\"64a5910e8ed78606ddbbb473\":true,\"64a5910e8ed78606ddbbb491\":true}},\"60a7812ca228635201070a83\":{\"vendorGrant\":true,\"purposeGrants\":{\"64a5910e8ed78606ddbbb3c9\":true,\"64a5910e8ed78606ddbbb3e9\":true,\"64a5910e8ed78606ddbbb44f\":true,\"64a5910e8ed78606ddbbb491\":true}},\"5ec515cab8e05c6bd60edc5f\":{\"vendorGrant\":true,\"purposeGrants\":{\"64a5910e8ed78606ddbbb3e9\":true,\"64a5910e8ed78606ddbbb425\":true,\"64a5910e8ed78606ddbbb46e\":true,\"64a5910e8ed78606ddbbb473\":true}},\"5e7ced57b8e05c47e418b74c\":{\"vendorGrant\":true,\"purposeGrants\":{\"64a5910e8ed78606ddbbb3e9\":true,\"64a5910e8ed78606ddbbb425\":true,\"64a5910e8ed78606ddbbb44f\":true,\"64a5910e8ed78606ddbbb491\":true}},\"5e37fc3e56a5e6615502f9c7\":{\"vendorGrant\":true,\"purposeGrants\":{\"64a5910e8ed78606ddbbb3e9\":true,\"64a5910e8ed78606ddbbb44f\":true,\"64a5910e8ed78606ddbbb491\":true}},\"5f92a628a228635d69558c37\":{\"vendorGrant\":true,\"purposeGrants\":{\"64a5910e8ed78606ddbbb3e9\":true,\"64a5910e8ed78606ddbbb44f\":true}},\"60cc6b2da228632d8e254476\":{\"vendorGrant\":true,\"purposeGrants\":{\"64a5910e8ed78606ddbbb44f\":true,\"64a5910e8ed78606ddbbb46e\":true,\"64a5910e8ed78606ddbbb491\":true}},\"6650c04a4f9aee5bdd32db5c\":{\"vendorGrant\":true,\"purposeGrants\":{\"64a5910e8ed78606ddbbb44f\":true,\"64a5910e8ed78606ddbbb46e\":true,\"64a5910e8ed78606ddbbb491\":true}},\"5e7ced57b8e05c485246ccf3\":{\"vendorGrant\":true,\"purposeGrants\":{\"64a5910e8ed78606ddbbb44f\":true,\"64a5910e8ed78606ddbbb491\":true}},\"5eab3d5bb8e05c48537f61a0\":{\"vendorGrant\":true,\"purposeGrants\":{\"64a5910e8ed78606ddbbb44f\":true}}},\"euconsent\":\"CQODbMAQODbMAAGABCENBfFgAPPAAELAAB5QH9wGAAGAAVABkAEeAJoAnABdADcAH4AQIA7gB7AEIAIsATsArIBaQC6gGmAROAvMBkgDfgH1AP7A36ASAD8AI4AfgB3AEIAIsAvMBtADfgBQkAUACoAMgB3AD2AZIOgEAAVABkAF0AdwA9gETgMkAf2QgBgDuAROA_slABAZIUgDgAVABkAH4AiwCJwGSAP7.YAAACFgAAAAA\",\"consentStatus\":{\"rejectedAny\":false,\"rejectedLI\":false,\"consentedAll\":true,\"granularStatus\":{\"vendorConsent\":\"ALL\",\"vendorLegInt\":\"ALL\",\"purposeConsent\":\"ALL\",\"purposeLegInt\":\"ALL\",\"previousOptInAll\":false,\"defaultConsent\":false},\"hasConsentData\":true,\"consentedToAny\":true},\"actions\":[],\"dateCreated\":\"2025-03-10T07:03:11.915Z\",\"vendorListId\":\"64a5910e4f9aee03581a973e\",\"expirationDate\":\"2026-03-10T07:03:11.915Z\",\"categories\":[\"64a5910e8ed78606ddbbb3c9\",\"64a5910e8ed78606ddbbb3e9\",\"64a5910e8ed78606ddbbb407\",\"64a5910e8ed78606ddbbb425\",\"64a5910e8ed78606ddbbb44f\",\"64a5910e8ed78606ddbbb46e\",\"64a5910e8ed78606ddbbb473\",\"64a5910e8ed78606ddbbb491\"],\"legIntCategories\":[\"64a5910e8ed78606ddbbb3e9\",\"64a5910e8ed78606ddbbb44f\",\"64a5910e8ed78606ddbbb473\",\"64a5910e8ed78606ddbbb491\"],\"vendors\":[\"5f1b2fbeb8e05c3057240fbc\",\"5f1b2fbdb8e05c306e139f26\",\"5f1b2fbeb8e05c306e139f60\",\"5ec515cab8e05c6bd60edc5f\",\"5e37fc3e56a5e66147767221\",\"5e865b36b8e05c48537f60a7\",\"5e7ced57b8e05c5a7d171cda\",\"5f2d22a6b8e05c02aa283b3b\",\"5efefe25b8e05c06542b2a77\",\"5e7ced57b8e05c485246cce2\",\"5e37fc3e56a5e6615502f9c5\",\"5f0838a5b8e05c109c2b8404\",\"5e37fc3e56a5e6615502f9c7\",\"5e37fc3e56a5e66147767233\",\"5f1aada5b8e05c306e139f01\",\"5f23e825b8e05c0ed30ea6ac\",\"5f117325b8e05c065164a42c\",\"5e7ced57b8e05c485246ccf3\",\"5e7ced57b8e05c47e418b74c\",\"5ee34ea4b8e05c16353f5bb7\",\"5f369a02b8e05c2f2d546a40\",\"5ef5c3a5b8e05c69980eaa5b\",\"5e37fc3e56a5e6615502f9c9\",\"6650c04a4f9aee5bdd32db5c\",\"5f1aada6b8e05c306c0597d7\",\"5f2d22a6b8e05c02aa283b3c\",\"5fa51b27a2286307ce61b623\",\"60a7812ca228635201070a83\",\"60cc6b2da228632d8e254476\",\"5eab3d5bb8e05c48537f61a0\",\"5f92a628a228635d69558c37\"],\"legIntVendors\":[\"5f1b2fbeb8e05c3057240fbc\",\"5f1b2fbdb8e05c306e139f26\",\"5f1b2fbeb8e05c306e139f60\",\"5eab3d5bb8e05c48537f61a0\",\"5f2d22a6b8e05c02aa283b3b\",\"5e37fc3e56a5e6615502f9c7\",\"5f1aada5b8e05c306e139f01\",\"5f117325b8e05c065164a42c\",\"5e7ced57b8e05c485246ccf3\",\"5f1aada6b8e05c306c0597d7\",\"5f92a628a228635d69558c37\",\"5fa51b27a2286307ce61b623\"],\"specialFeatures\":[]},\"usnat\":{\"authId\":\"1ed62e90-d98f-440c-80b8-16b04c25c3fd\",\"uuid\":\"b7abcd80-f61c-4a06-8bac-2ea98a11d901\",\"applicableSections\":[],\"applies\":false,\"legislation\":\"usnat\",\"categories\":[\"648c9c48e17a3c7a82360c54\",\"66585d5a658d37a934ac750a\"],\"dateCreated\":\"2025-03-10T07:40:10.454Z\",\"expirationDate\":\"2026-03-10T07:40:10.454Z\",\"consentStatus\":{\"rejectedAny\":false,\"consentedToAll\":true,\"consentedToAny\":false,\"granularStatus\":{\"sellStatus\":true,\"shareStatus\":true,\"sensitiveDataStatus\":false,\"gpcStatus\":false},\"hasConsentData\":false},\"consentStrings\":[{\"sectionId\":7,\"sectionName\":\"usnat\",\"consentString\":\"BVQqAAAAAgA\"}],\"userConsents\":{\"applies\":false,\"categories\":[{\"_id\":\"648c9c48e17a3c7a82360c54\",\"systemId\":3,\"consented\":true},{\"_id\":\"66585d5a658d37a934ac750a\",\"consented\":true}],\"vendors\":[{\"_id\":\"5e7ced57b8e05c47e418b74c\",\"consented\":true},{\"_id\":\"5fa51b27a2286307ce61b623\",\"consented\":true},{\"_id\":\"5e37fc3e56a5e6615502f9c5\",\"consented\":true},{\"_id\":\"6650c04a4f9aee5bdd32db5c\",\"consented\":true},{\"_id\":\"5f1aada5b8e05c306e139f01\",\"consented\":true},{\"_id\":\"5f1b2fbeb8e05c3057240fbc\",\"consented\":true},{\"_id\":\"5f1b2fbdb8e05c306e139f26\",\"consented\":true},{\"_id\":\"5f1b2fbeb8e05c306e139f60\",\"consented\":true},{\"_id\":\"60cc6b2da228632d8e254476\",\"consented\":true},{\"_id\":\"5e7ced57b8e05c5a7d171cda\",\"consented\":true},{\"_id\":\"5f117325b8e05c065164a42c\",\"consented\":true},{\"_id\":\"5e37fc3e56a5e66147767221\",\"consented\":true},{\"_id\":\"5e37fc3e56a5e6615502f9c9\",\"consented\":true},{\"_id\":\"5efefe25b8e05c06542b2a77\",\"consented\":true},{\"_id\":\"5e37fc3e56a5e6615502f9c7\",\"consented\":true},{\"_id\":\"5f0838a5b8e05c109c2b8404\",\"consented\":true},{\"_id\":\"5e7ced57b8e05c485246cce2\",\"consented\":true},{\"_id\":\"5f1aada6b8e05c306c0597d7\",\"consented\":true},{\"_id\":\"5e37fc3e56a5e66147767233\",\"consented\":true},{\"_id\":\"5f92a628a228635d69558c37\",\"consented\":true},{\"_id\":\"5f2d22a6b8e05c02aa283b3c\",\"consented\":true},{\"_id\":\"5eab3d5bb8e05c48537f61a0\",\"consented\":true},{\"_id\":\"5ef5c3a5b8e05c69980eaa5b\",\"consented\":true},{\"_id\":\"5f369a02b8e05c2f2d546a40\",\"consented\":true},{\"_id\":\"5f2d22a6b8e05c02aa283b3b\",\"consented\":true},{\"_id\":\"5e37fc3e56a5e66147767239\",\"consented\":true},{\"_id\":\"5f23e825b8e05c0ed30ea6ac\",\"consented\":true},{\"_id\":\"5ee34ea4b8e05c16353f5bb7\",\"consented\":true},{\"_id\":\"5e865b36b8e05c48537f60a7\",\"consented\":true},{\"_id\":\"60a7812ca228635201070a83\",\"consented\":true},{\"_id\":\"5ec515cab8e05c6bd60edc5f\",\"consented\":true},{\"_id\":\"5e7ced57b8e05c485246ccf3\",\"consented\":true}]},\"actions\":[{\"type\":\"inline\",\"url\":\"\",\"js\":\"const regions = {\\n            \\\"usnat\\\" : false\\n        };\\nlocalStorage.setItem(\\\"ft_sp_marketing_optout\\\",  JSON.stringify(regions));\",\"tagManager\":null,\"_id\":\"67c8a82f8a03fa22fd5350f0\"}]},\"version\":1}"}, {"name": "_chartbeat4", "value": "t=BYcqk2cavatCSpOkRDS9gJuQS8OT&E=5&x=0&c=0.16&y=8436&w=768"}, {"name": "_uetvid", "value": "4b252c60fd8311efa01bc36a5fdb7ee3"}, {"name": "ft_sp_marketing_optout", "value": "{\"usnat\":false}"}, {"name": "li_adsId", "value": "dd594f76-cc40-4df6-a1af-cb3a53d80a3a"}, {"name": "_cb_svref_expires", "value": "1741594371190"}]}]}